cog2tiles/__init__.py
cog2tiles/_version.py
cog2tiles/cli.py
cog2tiles/tiler.py
cog2tiles/utils.py
cog2tiles-0.0.4.dist-info/METADATA
cog2tiles-0.0.4.dist-info/WHEEL
cog2tiles-0.0.4.dist-info/entry_points.txt
cog2tiles-0.0.4.dist-info/licenses/LICENSE
cog2tiles-0.0.4.dist-info/RECORD
