Metadata-Version: 2.4
Name: cog2tiles
Version: 0.0.4
Summary: COG to web map tiles converter with concurrent processing
Project-URL: Homepage, https://github.com/kshitijrajsharma/cog2tiles
Project-URL: Repository, https://github.com/kshitijrajsharma/cog2tiles
Project-URL: Issues, https://github.com/kshitijrajsharma/cog2tiles/issues
Author-email: Kshitij Raj Sharma <krschap@duck.com>
License: MIT
License-File: LICENSE
Keywords: cog,geospatial,gis,mapping,raster,tiles
Classifier: Development Status :: 4 - Beta
Classifier: Intended Audience :: Developers
Classifier: Intended Audience :: Science/Research
Classifier: License :: OSI Approved :: MIT License
Classifier: Programming Language :: Python :: 3
Classifier: Programming Language :: Python :: 3.11
Classifier: Programming Language :: Python :: 3.12
Classifier: Programming Language :: Python :: 3.13
Classifier: Topic :: Scientific/Engineering :: GIS
Classifier: Topic :: Software Development :: Libraries :: Python Modules
Requires-Python: >=3.11
Requires-Dist: mercantile>=1.2.1
Requires-Dist: numba>=0.61.2
Requires-Dist: numpy>=2.2.6
Requires-Dist: pillow>=11.3.0
Requires-Dist: polars>=1.32.2
Requires-Dist: rasterio>=1.3.0
Requires-Dist: rio-tiler>=7.8.1
Requires-Dist: tqdm>=4.67.1
Requires-Dist: uvloop>=0.21.0; sys_platform != 'win32'
